helloworld.py
helloworld_algiras-0.0.1.dist-info/METADATA
helloworld_algiras-0.0.1.dist-info/RECORD
helloworld_algiras-0.0.1.dist-info/WHEEL
helloworld_algiras-0.0.1.dist-info/top_level.txt
