Metadata-Version: 2.1
Name: helloworld-algiras
Version: 0.0.1
Summary: Say hello
Home-page: https://github.com/Algiras/helloworld
Author: Algimantas Krasauskas
Author-email: kras.algim@gmail.com
License: UNKNOWN
Platform: UNKNOWN
Classifier: Programming Language :: Python :: 3
Classifier: Programming Language :: Python :: 3.6
Classifier: Programming Language :: Python :: 3.7
Classifier: License :: OSI Approved :: MIT License
Classifier: Operating System :: OS Independent
Requires-Dist: blessings (~=1.7)
